cosmologger/__init__.py
cosmologger-1.0.0.dist-info/LICENSE
cosmologger-1.0.0.dist-info/METADATA
cosmologger-1.0.0.dist-info/WHEEL
cosmologger-1.0.0.dist-info/top_level.txt
cosmologger-1.0.0.dist-info/RECORD
