Metadata-Version: 2.1
Name: cosmologger
Version: 1.0.0
Summary: A Nicely formatted Logger for the Cosmo Project
Home-page: https://github.com/SamHDev/cosmologger/
Author: SamHDev
Author-email: sam02h.huddart@gmail.com
License: UNKNOWN
Platform: UNKNOWN
Classifier: Programming Language :: Python :: 3
Classifier: Operating System :: OS Independent
